[{"buttonlabel": "cluster: 24", "col": "cluster", "val": 24}, {"buttonlabel": "cluster: 23", "col": "cluster", "val": 23}, {"buttonlabel": "cluster: 7", "col": "cluster", "val": 7}, {"buttonlabel": "cluster: 8", "col": "cluster", "val": 8}, {"buttonlabel": "cluster: 29", "col": "cluster", "val": 29}, {"buttonlabel": "cluster: 11", "col": "cluster", "val": 11}, {"buttonlabel": "cluster: 10", "col": "cluster", "val": 10}, {"buttonlabel": "cluster: 15", "col": "cluster", "val": 15}, {"buttonlabel": "cluster: 12", "col": "cluster", "val": 12}, {"buttonlabel": "cluster: 18", "col": "cluster", "val": 18}, {"buttonlabel": "cluster: 19", "col": "cluster", "val": 19}, {"buttonlabel": "cluster: 20", "col": "cluster", "val": 20}, {"buttonlabel": "cluster: 25", "col": "cluster", "val": 25}, {"buttonlabel": "cluster: 2", "col": "cluster", "val": 2}, {"buttonlabel": "cluster: 14", "col": "cluster", "val": 14}, {"buttonlabel": "cluster: 5", "col": "cluster", "val": 5}, {"buttonlabel": "cluster: 28", "col": "cluster", "val": 28}, {"buttonlabel": "cluster: 17", "col": "cluster", "val": 17}, {"buttonlabel": "cluster: 6", "col": "cluster", "val": 6}, {"buttonlabel": "cluster: 1", "col": "cluster", "val": 1}, {"buttonlabel": "cluster: 3", "col": "cluster", "val": 3}, {"buttonlabel": "cluster: 0", "col": "cluster", "val": 0}, {"buttonlabel": "cluster: 16", "col": "cluster", "val": 16}, {"buttonlabel": "cluster: 13", "col": "cluster", "val": 13}, {"buttonlabel": "cluster: 21", "col": "cluster", "val": 21}, {"buttonlabel": "cluster: 9", "col": "cluster", "val": 9}, {"buttonlabel": "cluster: 4", "col": "cluster", "val": 4}, {"buttonlabel": "cluster: 26", "col": "cluster", "val": 26}, {"buttonlabel": "cluster: 30", "col": "cluster", "val": 30}, {"buttonlabel": "cluster: 31", "col": "cluster", "val": 31}, {"buttonlabel": "cluster: 27", "col": "cluster", "val": 27}, {"buttonlabel": "cluster: 22", "col": "cluster", "val": 22}, {"buttonlabel": "location: Synagogue", "col": "location", "val": "Synagogue"}, {"buttonlabel": "location: Citadel", "col": "location", "val": "Citadel"}, {"buttonlabel": "location: Main Gate (Palmyrene Gate)", "col": "location", "val": "Main Gate (Palmyrene Gate)"}, {"buttonlabel": "location: Temple of Zeus Megistos", "col": "location", "val": "Temple of Zeus Megistos"}, {"buttonlabel": "location: Christian Building", "col": "location", "val": "Christian Building"}, {"buttonlabel": "location: Necropolis", "col": "location", "val": "Necropolis"}, {"buttonlabel": "location: Temple of Atargatis", "col": "location", "val": "Temple of Atargatis"}, {"buttonlabel": "location: Mithraeum", "col": "location", "val": "Mithraeum"}, {"buttonlabel": "location: Private Houses", "col": "location", "val": "Private Houses"}, {"buttonlabel": "location: Temple of Bel/Palmyrene Gods", "col": "location", "val": "Temple of Bel/Palmyrene Gods"}, {"buttonlabel": "location: Temple of Artemis", "col": "location", "val": "Temple of Artemis"}, {"buttonlabel": "location: Erzi", "col": "location", "val": "Erzi"}, {"buttonlabel": "location: Baghouz (Bahgus)", "col": "location", "val": "Baghouz (Bahgus)"}, {"buttonlabel": "location: Dolicheneum", "col": "location", "val": "Dolicheneum"}, {"buttonlabel": "location: Private house", "col": "location", "val": "Private house"}, {"buttonlabel": "location: Parthian Bath. Amphitheatre", "col": "location", "val": "Parthian Bath. Amphitheatre"}, {"buttonlabel": "location: Temple of Zeus Theos", "col": "location", "val": "Temple of Zeus Theos"}, {"buttonlabel": "location: Private Houses, shops", "col": "location", "val": "Private Houses, shops"}, {"buttonlabel": "location: Temple of Gadde", "col": "location", "val": "Temple of Gadde"}, {"buttonlabel": "location: Private houses, shops", "col": "location", "val": "Private houses, shops"}, {"buttonlabel": "location: Temple of the Gadde", "col": "location", "val": "Temple of the Gadde"}, {"buttonlabel": "location: Christian building; private houses", "col": "location", "val": "Christian building; private houses"}, {"buttonlabel": "location: Temple of Azzanathkona", "col": "location", "val": "Temple of Azzanathkona"}, {"buttonlabel": "location: Temple of Zeus Kyrios", "col": "location", "val": "Temple of Zeus Kyrios"}, {"buttonlabel": "location: Temple of Aphlad", "col": "location", "val": "Temple of Aphlad"}, {"buttonlabel": "location: House of Lysias", "col": "location", "val": "House of Lysias"}, {"buttonlabel": "location: Redoubt Palace", "col": "location", "val": "Redoubt Palace"}, {"buttonlabel": "location: Private Houses. Shops", "col": "location", "val": "Private Houses. Shops"}, {"buttonlabel": "location: Private Houses.  shops", "col": "location", "val": "Private Houses.  shops"}, {"buttonlabel": "location: Praetorium", "col": "location", "val": "Praetorium"}, {"buttonlabel": "location: private house", "col": "location", "val": "private house"}, {"buttonlabel": "location: Temple of Adonis", "col": "location", "val": "Temple of Adonis"}, {"buttonlabel": "location: Synagogue, Private Houses", "col": "location", "val": "Synagogue, Private Houses"}, {"buttonlabel": "location: Headquarters of Dux", "col": "location", "val": "Headquarters of Dux"}, {"buttonlabel": "location: synagogue", "col": "location", "val": "synagogue"}, {"buttonlabel": "location: Necropolis, Tomb 24-XIV", "col": "location", "val": "Necropolis, Tomb 24-XIV"}, {"buttonlabel": "location: private houses", "col": "location", "val": "private houses"}, {"buttonlabel": "location: Seleucid Shops", "col": "location", "val": "Seleucid Shops"}, {"buttonlabel": "location: Necropolis, Tomb 40", "col": "location", "val": "Necropolis, Tomb 40"}, {"buttonlabel": "location: Tower 19", "col": "location", "val": "Tower 19"}, {"buttonlabel": "location: Private house, shop", "col": "location", "val": "Private house, shop"}, {"buttonlabel": "location: Dux Palace", "col": "location", "val": "Dux Palace"}, {"buttonlabel": "location: private house/barracks", "col": "location", "val": "private house/barracks"}, {"buttonlabel": "location: Private houses, barracks", "col": "location", "val": "Private houses, barracks"}, {"buttonlabel": "location: Necr. Tomb 24 XIV", "col": "location", "val": "Necr. Tomb 24 XIV"}, {"buttonlabel": "location: Private House/Roman Bath", "col": "location", "val": "Private House/Roman Bath"}, {"buttonlabel": "location: Temple of Zeus", "col": "location", "val": "Temple of Zeus"}, {"buttonlabel": "location: Private House", "col": "location", "val": "Private House"}, {"buttonlabel": "location: House of Scribes", "col": "location", "val": "House of Scribes"}, {"buttonlabel": "location: Bath", "col": "location", "val": "Bath"}, {"buttonlabel": "location: Mithraeum, barracks", "col": "location", "val": "Mithraeum, barracks"}, {"buttonlabel": "location: Roman bath/private house", "col": "location", "val": "Roman bath/private house"}, {"buttonlabel": "location: Temple of Azzanathkona, Praetorium", "col": "location", "val": "Temple of Azzanathkona, Praetorium"}, {"buttonlabel": "location: Private houses", "col": "location", "val": "Private houses"}, {"buttonlabel": "location: Town", "col": "location", "val": "Town"}, {"buttonlabel": "location: Christian building; private house", "col": "location", "val": "Christian building; private house"}, {"buttonlabel": "location: House of Priests", "col": "location", "val": "House of Priests"}, {"buttonlabel": "location: Necropolis, Tomb 40-VI", "col": "location", "val": "Necropolis, Tomb 40-VI"}, {"buttonlabel": "date: Date of Photography: 1933-1934", "col": "date", "val": "Date of Photography: 1933-1934"}, {"buttonlabel": "date: Date of Photography: 1935-1936", "col": "date", "val": "Date of Photography: 1935-1936"}, {"buttonlabel": "date: Date of Photography: 1936-1937", "col": "date", "val": "Date of Photography: 1936-1937"}, {"buttonlabel": "date: Date of Photography: 1932-1933", "col": "date", "val": "Date of Photography: 1932-1933"}, {"buttonlabel": "date: Date of Photography: 1934-1935", "col": "date", "val": "Date of Photography: 1934-1935"}, {"buttonlabel": "date: Date of Photography: 1928-1929", "col": "date", "val": "Date of Photography: 1928-1929"}, {"buttonlabel": "date: Date of Photography: 1930-1931", "col": "date", "val": "Date of Photography: 1930-1931"}, {"buttonlabel": "date: Date of Photography: March 12, 2007", "col": "date", "val": "Date of Photography: March 12, 2007"}, {"buttonlabel": "date: Date of Photography: 1931-1932", "col": "date", "val": "Date of Photography: 1931-1932"}, {"buttonlabel": "date: Date of Photography: 1929-1930", "col": "date", "val": "Date of Photography: 1929-1930"}, {"buttonlabel": "date: Date of Photography: March 1946", "col": "date", "val": "Date of Photography: March 1946"}, {"buttonlabel": "date: Date of Photography: February 1946", "col": "date", "val": "Date of Photography: February 1946"}, {"buttonlabel": "date: Date of Photography: 1936", "col": "date", "val": "Date of Photography: 1936"}, {"buttonlabel": "date: Date of Photography: March 1967", "col": "date", "val": "Date of Photography: March 1967"}, {"buttonlabel": "date: Date of Photography: January 1946", "col": "date", "val": "Date of Photography: January 1946"}, {"buttonlabel": "date: Date of Photography: July 1946", "col": "date", "val": "Date of Photography: July 1946"}, {"buttonlabel": "date: Date of Photography: 1935", "col": "date", "val": "Date of Photography: 1935"}, {"buttonlabel": "date: Date of Photography: 1933", "col": "date", "val": "Date of Photography: 1933"}, {"buttonlabel": "date: Date of Photography: 1931-1932 or 1932-1933", "col": "date", "val": "Date of Photography: 1931-1932 or 1932-1933"}, {"buttonlabel": "date: Roman CE 216", "col": "date", "val": "Roman CE 216"}, {"buttonlabel": "date: Date of Photography: 1929", "col": "date", "val": "Date of Photography: 1929"}, {"buttonlabel": "date: Date of Photography: 1934", "col": "date", "val": "Date of Photography: 1934"}, {"buttonlabel": "date: Date of Photography: 1933-1935", "col": "date", "val": "Date of Photography: 1933-1935"}, {"buttonlabel": "date: Date of Photography: 1931", "col": "date", "val": "Date of Photography: 1931"}, {"buttonlabel": "date: Date of Photography: 1932", "col": "date", "val": "Date of Photography: 1932"}, {"buttonlabel": "date: Roman CE iii  [CBW]", "col": "date", "val": "Roman CE iii  [CBW]"}, {"buttonlabel": "date: Date of Photography: July 1955", "col": "date", "val": "Date of Photography: July 1955"}, {"buttonlabel": "date: Date of Photography: 1937", "col": "date", "val": "Date of Photography: 1937"}, {"buttonlabel": "date: Date of Photography: July 1945", "col": "date", "val": "Date of Photography: July 1945"}, {"buttonlabel": "image_source: plan/drawing/reconstruction", "col": "image_source", "val": "plan/drawing/reconstruction"}, {"buttonlabel": "image_source: Damascus photo", "col": "image_source", "val": "Damascus photo"}, {"buttonlabel": "image_source: digital", "col": "image_source", "val": "digital"}, {"buttonlabel": "image_source: YUAG Photo", "col": "image_source", "val": "YUAG Photo"}, {"buttonlabel": "creation_site: Creation Site: Gerasa (Jerash)", "col": "creation_site", "val": "Creation Site: Gerasa (Jerash)"}, {"buttonlabel": "image_type: digital", "col": "image_type", "val": "digital"}, {"buttonlabel": "image_type: nitrate negative", "col": "image_type", "val": "nitrate negative"}, {"buttonlabel": "image_type: replacement negative", "col": "image_type", "val": "replacement negative"}, {"buttonlabel": "image_type: color slide", "col": "image_type", "val": "color slide"}, {"buttonlabel": "image_type: bw slide", "col": "image_type", "val": "bw slide"}, {"buttonlabel": "image_type: color transparency", "col": "image_type", "val": "color transparency"}, {"buttonlabel": "language: Latin", "col": "language", "val": "Latin"}, {"buttonlabel": "language: Greek", "col": "language", "val": "Greek"}, {"buttonlabel": "language: Latin; Greek", "col": "language", "val": "Latin; Greek"}, {"buttonlabel": "type: Letter", "col": "type", "val": "Letter"}, {"buttonlabel": "type: List", "col": "type", "val": "List"}, {"buttonlabel": "type: Contract", "col": "type", "val": "Contract"}, {"buttonlabel": "type: Document", "col": "type", "val": "Document"}, {"buttonlabel": "photographer: Toll", "col": "photographer", "val": "Toll"}, {"buttonlabel": "photographer: liz", "col": "photographer", "val": "liz"}, {"buttonlabel": "photographer: de Cusati", "col": "photographer", "val": "de Cusati"}, {"buttonlabel": "photographer: Richards", "col": "photographer", "val": "Richards"}, {"buttonlabel": "photographer: Kraeling", "col": "photographer", "val": "Kraeling"}, {"buttonlabel": "photographer: Keane", "col": "photographer", "val": "Keane"}, {"buttonlabel": "photographer: D. Richards", "col": "photographer", "val": "D. Richards"}, {"buttonlabel": "repository: Beinecke Rare Book and Manuscript Library, Yale University", "col": "repository", "val": "Beinecke Rare Book and Manuscript Library, Yale University"}]